gym_examples/__init__.py
gym_examples/envs/__init__.py
gym_examples/envs/grid_world.py
gym_examples/wrappers/__init__.py
gym_examples/wrappers/clip_reward.py
gym_examples/wrappers/discrete_actions.py
gym_examples/wrappers/reacher_weighted_reward.py
gym_examples/wrappers/relative_position.py
gym_examples_anza4273-0.0.2.dist-info/METADATA
gym_examples_anza4273-0.0.2.dist-info/WHEEL
gym_examples_anza4273-0.0.2.dist-info/top_level.txt
gym_examples_anza4273-0.0.2.dist-info/RECORD
