Metadata-Version: 2.1
Name: gym-examples-anza4273
Version: 0.0.2
Requires-Dist: gym (==0.26.0)
Requires-Dist: pygame (==2.1.0)
